{"assets/breakfast/apple_spina.png":["assets/breakfast/apple_spina.png"],"assets/breakfast/apple_spina1.png":["assets/breakfast/apple_spina1.png"],"assets/breakfast/avocado_waffle.png":["assets/breakfast/avocado_waffle.png"],"assets/breakfast/belgium.png":["assets/breakfast/belgium.png"],"assets/breakfast/bowl_las.png":["assets/breakfast/bowl_las.png"],"assets/breakfast/bowl_shrimp.png":["assets/breakfast/bowl_shrimp.png"],"assets/breakfast/breakfast1.png":["assets/breakfast/breakfast1.png"],"assets/breakfast/breakfast3.png":["assets/breakfast/breakfast3.png"],"assets/breakfast/breakfast4.png":["assets/breakfast/breakfast4.png"],"assets/breakfast/desserts.png":["assets/breakfast/desserts.png"],"assets/breakfast/eggs.png":["assets/breakfast/eggs.png"],"assets/breakfast/granola.png":["assets/breakfast/granola.png"],"assets/breakfast/granola1.png":["assets/breakfast/granola1.png"],"assets/breakfast/omlet.png":["assets/breakfast/omlet.png"],"assets/breakfast/pancake.png":["assets/breakfast/pancake.png"],"assets/breakfast/pancake_straw.png":["assets/breakfast/pancake_straw.png"],"assets/breakfast/pear.png":["assets/breakfast/pear.png"],"assets/breakfast/pear1.png":["assets/breakfast/pear1.png"],"assets/breakfast/pita_las.png":["assets/breakfast/pita_las.png"],"assets/breakfast/pita_tel.png":["assets/breakfast/pita_tel.png"],"assets/breakfast/poke_kur.png":["assets/breakfast/poke_kur.png"],"assets/breakfast/syrniki.png":["assets/breakfast/syrniki.png"],"assets/breakfast/vareniki.png":["assets/breakfast/vareniki.png"],"assets/breakfast/waffle_spin.png":["assets/breakfast/waffle_spin.png"],"assets/burgers/bbq.png":["assets/burgers/bbq.png"],"assets/burgers/chicken.png":["assets/burgers/chicken.png"],"assets/burgers/kla.png":["assets/burgers/kla.png"],"assets/coffee_cup.jpg":["assets/coffee_cup.jpg"],"assets/garnirs/brokoli.png":["assets/garnirs/brokoli.png"],"assets/garnirs/dolki.png":["assets/garnirs/dolki.png"],"assets/garnirs/free.png":["assets/garnirs/free.png"],"assets/garnirs/kartofel.png":["assets/garnirs/kartofel.png"],"assets/garnirs/pure.png":["assets/garnirs/pure.png"],"assets/garnirs/razmarin.png":["assets/garnirs/razmarin.png"],"assets/garnirs/vegetables.png":["assets/garnirs/vegetables.png"],"assets/main_food.jpg":["assets/main_food.jpg"],"assets/main_food/baran.png":["assets/main_food/baran.png"],"assets/main_food/befstro.png":["assets/main_food/befstro.png"],"assets/main_food/chicken.png":["assets/main_food/chicken.png"],"assets/main_food/forel.png":["assets/main_food/forel.png"],"assets/main_food/medal.png":["assets/main_food/medal.png"],"assets/main_food/nioki.png":["assets/main_food/nioki.png"],"assets/main_food/ribay.png":["assets/main_food/ribay.png"],"assets/main_food/rice.png":["assets/main_food/rice.png"],"assets/main_food/salmon_ikra.png":["assets/main_food/salmon_ikra.png"],"assets/main_food/steak_salm.png":["assets/main_food/steak_salm.png"],"assets/main_food/tibon.png":["assets/main_food/tibon.png"],"assets/main_food/tongue.png":["assets/main_food/tongue.png"],"assets/pastas/balon.png":["assets/pastas/balon.png"],"assets/pastas/fet_kur.png":["assets/pastas/fet_kur.png"],"assets/pastas/fet_las.png":["assets/pastas/fet_las.png"],"assets/pastas/fet_more.png":["assets/pastas/fet_more.png"],"assets/pastas/konfeti.png":["assets/pastas/konfeti.png"],"assets/pastas/mushroom.png":["assets/pastas/mushroom.png"],"assets/pastas/past_kur.png":["assets/pastas/past_kur.png"],"assets/pastas/rav_kartofel.png":["assets/pastas/rav_kartofel.png"],"assets/pastas/ravioli_las.png":["assets/pastas/ravioli_las.png"],"assets/pastas/rukola.png":["assets/pastas/rukola.png"],"assets/salads/avocado-min.png":["assets/salads/avocado-min.png"],"assets/salads/eggplant-min.png":["assets/salads/eggplant-min.png"],"assets/salads/french-min.png":["assets/salads/french-min.png"],"assets/salads/kon-min.png":["assets/salads/kon-min.png"],"assets/salads/las-min.png":["assets/salads/las-min.png"],"assets/salads/more-min.png":["assets/salads/more-min.png"],"assets/salads/muss-min.png":["assets/salads/muss-min.png"],"assets/salads/pump-min.png":["assets/salads/pump-min.png"],"assets/salads/razno-min.png":["assets/salads/razno-min.png"],"assets/salads/rukkola-min.png":["assets/salads/rukkola-min.png"],"assets/salads/sezar-min.png":["assets/salads/sezar-min.png"],"assets/salads/shop-min.png":["assets/salads/shop-min.png"],"assets/salads/svekla-min.png":["assets/salads/svekla-min.png"],"assets/salads/vitam-min.png":["assets/salads/vitam-min.png"],"assets/snacks/bak.png":["assets/snacks/bak.png"],"assets/snacks/brusket.png":["assets/snacks/brusket.png"],"assets/snacks/buter_tep.png":["assets/snacks/buter_tep.png"],"assets/snacks/corn.png":["assets/snacks/corn.png"],"assets/snacks/humus.png":["assets/snacks/humus.png"],"assets/snacks/kapreze.png":["assets/snacks/kapreze.png"],"assets/snacks/kruasan_ben.png":["assets/snacks/kruasan_ben.png"],"assets/snacks/kruasan_sem.png":["assets/snacks/kruasan_sem.png"],"assets/snacks/min_bur.png":["assets/snacks/min_bur.png"],"assets/snacks/panini.png":["assets/snacks/panini.png"],"assets/snacks/pashtet.png":["assets/snacks/pashtet.png"],"assets/snacks/pit-las.png":["assets/snacks/pit-las.png"],"assets/snacks/pita_tel.png":["assets/snacks/pita_tel.png"],"assets/snacks/roll_sezar.png":["assets/snacks/roll_sezar.png"],"assets/snacks/rulet.png":["assets/snacks/rulet.png"],"assets/snacks/sendwich.png":["assets/snacks/sendwich.png"],"assets/snacks/shakshuka.png":["assets/snacks/shakshuka.png"],"assets/snacks/zakuska.png":["assets/snacks/zakuska.png"],"assets/snacks/zukini.png":["assets/snacks/zukini.png"],"assets/soups/borsh.png":["assets/soups/borsh.png"],"assets/soups/cheche.png":["assets/soups/cheche.png"],"assets/soups/chicken soup.png":["assets/soups/chicken soup.png"],"assets/soups/mushroom.png":["assets/soups/mushroom.png"],"assets/soups/okrosh.png":["assets/soups/okrosh.png"],"assets/soups/pelmeni.png":["assets/soups/pelmeni.png"],"assets/soups/pumpkin.png":["assets/soups/pumpkin.png"],"assets/soups/solanka.png":["assets/soups/solanka.png"],"assets/soups/tom.png":["assets/soups/tom.png"],"assets/soups/tomat.png":["assets/soups/tomat.png"],"assets/soups/uha.png":["assets/soups/uha.png"],"packages/cupertino_icons/assets/CupertinoIcons.ttf":["packages/cupertino_icons/assets/CupertinoIcons.ttf"]}